CHANGELOG.txt
LICENCE.txt
MANIFEST.in
README.txt
setup.py
Pyvshale/_init_.py
Pyvshale/conf.py
Pyvshale/miscfuncs.py
Pyvshale/run_test.py
Pyvshale/temperature.py
Pyvshale/unit_conv.py
pyvshale.egg-info/PKG-INFO
pyvshale.egg-info/SOURCES.txt
pyvshale.egg-info/dependency_links.txt
pyvshale.egg-info/top_level.txt